refinery/AUTHORS.TXT
refinery/CHANGELOG.MD
refinery/LICENSE
refinery/README.MD
refinery/__init__.py
refinery/__main__.py
refinery/constants.py
refinery/core.py
refinery/crc_functions.py
refinery/editor_constants.py
refinery/exceptions.py
refinery/main.py
refinery/queue_item.py
refinery/refinery.ico
refinery/refinery.png
refinery/repl_run.py
refinery/run.py
refinery/tag_paths_to_never_rename.txt
refinery/test_commands.txt
refinery/util.py
refinery/defs/__init__.py
refinery/defs/config_def.py
refinery/heuristic_deprotection/__init__.py
refinery/heuristic_deprotection/constants.py
refinery/heuristic_deprotection/functions.py
refinery/heuristic_deprotection/util.py
refinery/repl/__init__.py
refinery/repl/arg_parsers.py
refinery/repl/help_strs.py
refinery/repl/util.py
refinery/tag_index/__init__.py
refinery/tag_index/tag_path_detokenizer.py
refinery/tag_index/tag_path_handler.py
refinery/tag_index/tag_path_tokens.py
refinery/widgets/__init__.py
refinery/widgets/explorer_class_tree.py
refinery/widgets/explorer_hierarchy_tree.py
refinery/widgets/explorer_hybrid_tree.py
refinery/widgets/queue_tree.py
refinery/windows/__init__.py
refinery/windows/actions_window.py
refinery/windows/crc_window.py
refinery/windows/meta_window.py
refinery/windows/rename_window.py
refinery/windows/settings_window.py
refinery-2.6.0.dist-info/AUTHORS.TXT
refinery-2.6.0.dist-info/LICENSE
refinery-2.6.0.dist-info/METADATA
refinery-2.6.0.dist-info/WHEEL
refinery-2.6.0.dist-info/top_level.txt
refinery-2.6.0.dist-info/RECORD
