Metadata-Version: 2.1
Name: refinery
Version: 2.6.0
Summary: A map extractor for games built with the Blam engine
Home-page: https://github.com/Sigmmma/refinery
Author: Sigmmma
Author-email: MoeMakesStuff@gmail.com
License: GPLv3
Project-URL: Source, https://github.com/Sigmmma/refinery
Project-URL: Funding, https://liberapay.com/MEK/
Keywords: refinery,halo,extraction
Platform: POSIX
Platform: Windows
Classifier: Development Status :: 4 - Beta
Classifier: Intended Audience :: End Users/Desktop
Classifier: License :: OSI Approved :: GNU General Public License v3 (GPLv3)
Classifier: Programming Language :: Python
Classifier: Programming Language :: Python :: 3
Classifier: Programming Language :: Python :: 3.5
Classifier: Programming Language :: Python :: 3.6
Classifier: Programming Language :: Python :: 3.7
Classifier: Programming Language :: Python :: 3.8
Classifier: Programming Language :: Python :: 3.9
Classifier: Programming Language :: Python :: 3 :: Only
Requires: mozzarilla
Requires: supyr_struct
Requires: reclaimer
Requires: binilla
Provides: refinery
Requires-Python: >=3.6
Requires-Dist: mozzarilla
Requires-Dist: supyr-struct
Requires-Dist: reclaimer
Requires-Dist: binilla
